ckanext_fuseki-1.0.6-py3.13-nspkg.pth
ckanext/fuseki/__init__.py
ckanext/fuseki/backend.py
ckanext/fuseki/db.py
ckanext/fuseki/helpers.py
ckanext/fuseki/plugin.py
ckanext/fuseki/tasks.py
ckanext/fuseki/views.py
ckanext/fuseki/assets/fuseki.js
ckanext/fuseki/assets/webassets.yml
ckanext/fuseki/i18n/de/LC_MESSAGES/ckanext-fuseki.mo
ckanext/fuseki/logic/__init__.py
ckanext/fuseki/logic/action.py
ckanext/fuseki/logic/auth.py
ckanext/fuseki/templates/fuseki/status.html
ckanext/fuseki/templates/package/read_base.html
ckanext/fuseki/templates/package/resource_read.html
ckanext/fuseki/templates/package/snippets/resource_item.html
ckanext_fuseki-1.0.6.dist-info/licenses/LICENSE
ckanext_fuseki-1.0.6.dist-info/METADATA
ckanext_fuseki-1.0.6.dist-info/WHEEL
ckanext_fuseki-1.0.6.dist-info/entry_points.txt
ckanext_fuseki-1.0.6.dist-info/namespace_packages.txt
ckanext_fuseki-1.0.6.dist-info/top_level.txt
ckanext_fuseki-1.0.6.dist-info/RECORD
