Metadata-Version: 2.4
Name: ckanext-fuseki
Version: 1.0.6
Summary: An extension for storing file with Apache Jena
Home-page: https://github.com/Mat-O-Lab/ckanext-fuseki
Author: Thomas Hanke
Author-email: thomas.hanke@iwm.fraunhofer.de
License: AGPL
Keywords: CKAN
Classifier: Development Status :: 4 - Beta
Classifier: License :: OSI Approved :: GNU Affero General Public License v3 or later (AGPLv3+)
Classifier: Programming Language :: Python :: 3.11
License-File: LICENSE
Requires-Dist: ckanapi
Requires-Dist: requests>=2.4.2
Requires-Dist: sqlalchemy
Requires-Dist: pytest
Requires-Dist: pytest-ckan
Requires-Dist: rdflib
Requires-Dist: requests_toolbelt
Dynamic: author
Dynamic: author-email
Dynamic: classifier
Dynamic: description
Dynamic: description-content-type
Dynamic: home-page
Dynamic: keywords
Dynamic: license
Dynamic: license-file
Dynamic: requires-dist
Dynamic: summary
